Metadata-Version: 2.1
Name: django-constant
Version: 1.0.0
Summary: This is a Django app designed to store global constants with different data types. It provides a central location to manage and access configuration values that can be easily reused throughout your Django project.
Home-page: https://github.com/yashmarathe21/django-constants
Author: Yash Marathe
Author-email: yashmarathe21@gmail.com
License: MIT
Keywords: django python constants
Classifier: License :: OSI Approved :: MIT License
Classifier: Programming Language :: Python :: 3
Classifier: Operating System :: OS Independent
Classifier: Framework :: Django
Classifier: Framework :: Django :: 3.2
Requires-Python: >=3.6
License-File: LICENSE.md
